RailsZhinan/README.md
RailsZhinan/__init__.py
RailsZhinan/__main__.py
RailsZhinan/file.epub
RailsZhinan/index.html
RailsZhinan/css/__init__.py
RailsZhinan/css/annotations.css
RailsZhinan/css/main.css
RailsZhinan/css/normalize.css
RailsZhinan/css/popup.css
RailsZhinan/font/__init__.py
RailsZhinan/font/fontello.eot
RailsZhinan/font/fontello.svg
RailsZhinan/font/fontello.ttf
RailsZhinan/font/fontello.woff
RailsZhinan/img/__init__.py
RailsZhinan/img/annotator-glyph-sprite.png
RailsZhinan/img/annotator-icon-sprite.png
RailsZhinan/img/apple-touch-icon.png
RailsZhinan/img/cancelfullscreen.png
RailsZhinan/img/close.png
RailsZhinan/img/fullscreen.png
RailsZhinan/img/loader.gif
RailsZhinan/img/menu-icon.png
RailsZhinan/img/save.png
RailsZhinan/img/saved.png
RailsZhinan/img/settings-s.png
RailsZhinan/img/settings.png
RailsZhinan/img/star.png
RailsZhinan/js/__init__.py
RailsZhinan/js/epub.js
RailsZhinan/js/epub.min.js
RailsZhinan/js/epub.min.map
RailsZhinan/js/hooks.min.js
RailsZhinan/js/hooks.min.map
RailsZhinan/js/reader.js
RailsZhinan/js/reader.js.map
RailsZhinan/js/reader.min.js
RailsZhinan/js/reader.min.map
RailsZhinan/js/hooks/__init__.py
RailsZhinan/js/hooks/extensions/__init__.py
RailsZhinan/js/hooks/extensions/highlight.js
RailsZhinan/js/libs/__init__.py
RailsZhinan/js/libs/jquery.min.js
RailsZhinan/js/libs/localforage.min.js
RailsZhinan/js/libs/screenfull.js
RailsZhinan/js/libs/screenfull.min.js
RailsZhinan/js/libs/zip.min.js
RailsZhinan/js/plugins/__init__.py
RailsZhinan/js/plugins/hypothesis.js
RailsZhinan/js/plugins/search.js
rails_zhinan-2024.3.2.0.dist-info/METADATA
rails_zhinan-2024.3.2.0.dist-info/WHEEL
rails_zhinan-2024.3.2.0.dist-info/entry_points.txt
rails_zhinan-2024.3.2.0.dist-info/top_level.txt
rails_zhinan-2024.3.2.0.dist-info/RECORD
